dsf_quantum_sdk/__init__.py
dsf_quantum_sdk/client.py
dsf_quantum_sdk/exceptions.py
dsf_quantum_sdk/models.py
dsf_quantum_sdk-1.1.0.dist-info/licenses/LICENSE
dsf_quantum_sdk-1.1.0.dist-info/METADATA
dsf_quantum_sdk-1.1.0.dist-info/WHEEL
dsf_quantum_sdk-1.1.0.dist-info/top_level.txt
dsf_quantum_sdk-1.1.0.dist-info/RECORD
