Metadata-Version: 2.4
Name: dsf-quantum-sdk
Version: 1.1.0
Summary: Lightweight SDK for DSF Quantum Adaptive Scoring with IBM Quantum support
Home-page: https://github.com/jaimeajl/dsf-quantum-sdk
Author: Jaime Alexander Jimenez
Author-email: contacto@dsfuptech.cloud
Project-URL: Bug Tracker, https://github.com/jaimeajl/dsf-quantum-sdk/issues
Project-URL: Documentation, https://docs.jaimeajl.com/dsf-quantum-sdk
Project-URL: Source Code, https://github.com/jaimeajl/dsf-quantum-sdk
Project-URL: Examples, https://github.com/jaimeajl/dsf-quantum-sdk/tree/main/examples
Keywords: quantum,quantum computing,ibm quantum,qiskit,adaptive scoring,hierarchical evaluation,quantum amplitude estimation,qae,dsf,decision support,machine learning
Classifier: Development Status :: 4 - Beta
Classifier: Intended Audience :: Developers
Classifier: Intended Audience :: Science/Research
Classifier: Topic :: Software Development :: Libraries :: Python Modules
Classifier: Topic :: Scientific/Engineering :: Physics
Classifier: Topic :: Scientific/Engineering :: Artificial Intelligence
Classifier: License :: Other/Proprietary License
Classifier: Programming Language :: Python :: 3
Classifier: Programming Language :: Python :: 3.8
Classifier: Programming Language :: Python :: 3.9
Classifier: Programming Language :: Python :: 3.10
Classifier: Programming Language :: Python :: 3.11
Classifier: Programming Language :: Python :: 3.12
Classifier: Operating System :: OS Independent
Requires-Python: >=3.8
License-File: LICENSE
Requires-Dist: requests>=2.25.0
Provides-Extra: dev
Requires-Dist: pytest>=7.0; extra == "dev"
Requires-Dist: pytest-cov>=3.0; extra == "dev"
Requires-Dist: black>=22.0; extra == "dev"
Requires-Dist: flake8>=4.0; extra == "dev"
Requires-Dist: mypy>=0.950; extra == "dev"
Requires-Dist: pytest-asyncio>=0.18; extra == "dev"
Dynamic: author
Dynamic: author-email
Dynamic: classifier
Dynamic: description
Dynamic: description-content-type
Dynamic: home-page
Dynamic: keywords
Dynamic: license-file
Dynamic: project-url
Dynamic: provides-extra
Dynamic: requires-dist
Dynamic: requires-python
Dynamic: summary
